indoNLP/__init__.py
indoNLP/dataset/__init__.py
indoNLP/dataset/downloader.py
indoNLP/dataset/list.py
indoNLP/dataset/reader.py
indoNLP/dataset/utils.py
indoNLP/preprocessing/__init__.py
indoNLP/preprocessing/emoji/__init__.py
indoNLP/preprocessing/emoji/emoji_data.py
indoNLP/preprocessing/slang_data.py
indoNLP/preprocessing/stopwords_data.py
indoNLP/py.typed
indonlp-0.3.3.dist-info/LICENSE
indonlp-0.3.3.dist-info/WHEEL
indonlp-0.3.3.dist-info/METADATA
indonlp-0.3.3.dist-info/RECORD
