Metadata-Version: 2.1
Name: indonlp
Version: 0.3.3
Summary: Simple python library with zero additional dependencies to make your Indonesian NLP project easier.
License: MIT
Keywords: indoNLP,nlp,indonesian-language
Author: Wahyu Setianto
Author-email: wahyusetianto19@gmail.com
Requires-Python: >=3.7,<4.0
Classifier: Development Status :: 5 - Production/Stable
Classifier: License :: OSI Approved :: MIT License
Classifier: Natural Language :: Indonesian
Classifier: Programming Language :: Python :: 3
Classifier: Programming Language :: Python :: 3.10
Classifier: Programming Language :: Python :: 3.7
Classifier: Programming Language :: Python :: 3.8
Classifier: Programming Language :: Python :: 3.9
Classifier: Topic :: Scientific/Engineering
Classifier: Topic :: Software Development :: Libraries
Classifier: Typing :: Typed
Project-URL: homepage, https://Hyuto.github.io/indo-nlp/
Project-URL: repository, https://github.com/Hyuto/indo-nlp
